Metadata-Version: 2.1
Name: DiskVectorIndex
Version: 0.0.2
Summary: Efficient vector DB on large datasets from disk, using minimal memory.
Home-page: https://github.com/cohere-ai/DiskVectorIndex
Download-URL: https://github.com/cohere-ai/DiskVectorIndex/
Author: Nils Reimers
Author-email: nils@cohere.com
License: Apache License 2.0
Keywords: Vector Database
Classifier: Development Status :: 4 - Beta
Classifier: Intended Audience :: Science/Research
Classifier: License :: OSI Approved :: Apache Software License
Classifier: Programming Language :: Python :: 3.9
Classifier: Topic :: Scientific/Engineering :: Artificial Intelligence
License-File: LICENSE
